{
  "Digital_IO_List": [
    {
      "Address": "X100",
      "Index": "DI_EMO_FRONT",
      "Description": "EMO Switch(Front)",
      "Type": "N.O",
      "IoCategory": "Digital Input"
    },
    {
      "Address": "X101",
      "Index": "DI_EMO_LEFT",
      "Description": "EMO Switch(Left)",
      "Type": "N.O",
      "IoCategory": "Digital Input"
    },
    {
      "Address": "X102",
      "Index": "DI_EMO_RIGHT",
      "Description": "EMO Switch(Right)",
      "Type": "N.O",
      "IoCategory": "Digital Input"
    },
    {
      "Address": "X103",
      "Index": "DI_EMO_BACK",
      "Description": "EMO Switch(Back)",
      "Type": "N.O",
      "IoCategory": "Digital Input"
    },
    {
      "Address": "X104",
      "Index": "DI_MC_ON_SIGNAL",
      "Description": "MC On Signal",
      "Type": "N.O",
      "IoCategory": "Digital Input"
    },
    {
      "Address": "X105",
      "Index": "DI_SMOKE_ALARM",
      "Description": "Smoke Alarm",
      "Type": "N.O",
      "IoCategory": "Digital Input"
    },
    {
      "Address": "X106",
      "Index": "DI_TEMP_ALARM",
      "Description": "Temp Alarm",
      "Type": "N.O",
      "IoCategory": "Digital Input"
    },
    {
      "Address": "X107",
      "Index": "DI_SAFETY_KEY",
      "Description": "SAFETY KEY AUTO/MANUAL",
      "Type": "N.O",
      "IoCategory": "Digital Input"
    },
    {
      "Address": "X108",
      "Index": "DI_DOOR_LOCK_ALL",
      "Description": "Door All Lock Check",
      "Type": "N.O",
      "IoCategory": "Digital Input"
    },
    {
      "Address": "X109",
      "Index": "DI_DOOR_LOCK_FRONT_LEFT",
      "Description": "Door Lock Check(FRONT / LEFT)",
      "Type": "N.O",
      "IoCategory": "Digital Input"
    },
    {
      "Address": "X110",
      "Index": "DI_DOOR_LOCK_FRONT_RIGHT",
      "Description": "Door Lock Check(FRONT / RIGHT)",
      "Type": "N.O",
      "IoCategory": "Digital Input"
    },
    {
      "Address": "X111",
      "Index": "DI_DOOR_LOCK_LEFT_LEFT",
      "Description": "Door Lock Check(LEFT / LEFT)",
      "Type": "N.O",
      "IoCategory": "Digital Input"
    },
    {
      "Address": "X112",
      "Index": "DI_DOOR_LOCK_LEFT_RIGHT",
      "Description": "Door Lock Check(LEFT / RIGHT)",
      "Type": "N.O",
      "IoCategory": "Digital Input"
    },
    {
      "Address": "X113",
      "Index": "DI_DOOR_LOCK_RIGHT_LEFT",
      "Description": "Door Lock Check(RIGHT / LEFT)",
      "Type": "N.O",
      "IoCategory": "Digital Input"
    },
    {
      "Address": "X114",
      "Index": "DI_DOOR_LOCK_RIGHT_RIGHT",
      "Description": "Door Lock Check(RIGHT / RIGHT)",
      "Type": "N.O",
      "IoCategory": "Digital Input"
    },
    {
      "Address": "X115",
      "Index": "DI_DOOR_LOCK_BACK_LEFT",
      "Description": "Door Lock Check(BACK UP / LEFT)",
      "Type": "N.O",
      "IoCategory": "Digital Input"
    },
    {
      "Address": "X200",
      "Index": "DI_DOOR_LOCK_BACK_RIGHT",
      "Description": "Door Lock Check(BACK UP / RIGHT)",
      "Type": "N.O",
      "IoCategory": "Digital Input"
    },
    {
      "Address": "X201",
      "Index": "DI_EMO_INNER_FRONT_RIGHT",
      "Description": "EMO Switch(Inner Front Right)",
      "Type": "N.O",
      "IoCategory": "Digital Input"
    },
    {
      "Address": "X202",
      "Index": "DI_EMO_INNER_BACK_LEFT",
      "Description": "EMO Switch(Inner Back Left)",
      "Type": "N.O",
      "IoCategory": "Digital Input"
    },
    {
      "Address": "X203",
      "Index": "DI_BOTTLE_1_LEVEL_SENSOR_HIGH",
      "Description": "Level Sensor HIGH(Bottle_1_BOX)",
      "Type": "N.C",
      "IoCategory": "Digital Input"
    },
    {
      "Address": "X204",
      "Index": "DI_BOTTLE_1_DETECT_SENSOR",
      "Description": "Detect Sensor(Bottle_1_BOX)",
      "Type": "N.O",
      "IoCategory": "Digital Input"
    },
    {
      "Address": "X205",
      "Index": "DI_BOTTLE_1_LEAK_SENSOR",
      "Description": "Leak Sensor(Bottle_1_BOX)",
      "Type": "N.C",
      "IoCategory": "Digital Input"
    },
    {
      "Address": "X206",
      "Index": "DI_OVERFLOW_SENSOR",
      "Description": "Overflow Sensor(Separator VAC Overflow)",
      "Type": "N.C",
      "IoCategory": "Digital Input"
    },
    {
      "Address": "X207",
      "Index": "DI_CONVAYOR_DETECT_SENSOR",
      "Description": "이송 컨베어 감지 Sensor",
      "Type": "N.O",
      "IoCategory": "Digital Input"
    },
    {
      "Address": "X208",
      "Index": "DI_PRESSURE_SW1_N2_IMS_AIR_KNIFE",
      "Description": "Pressure Switch <1>",
      "Type": "N.O",
      "IoCategory": "Digital Input"
    },
    {
      "Address": "X209",
      "Index": "DI_PRESSURE_SW2_CDA_IMS_N_EJEC",
      "Description": "Pressure Switch <2>",
      "Type": "N.O",
      "IoCategory": "Digital Input"
    },
    {
      "Address": "X210",
      "Index": "DI_PRESSURE_SW3_CDA_HM_SOL_P_MT_P",
      "Description": "Pressure Switch <3>",
      "Type": "N.O",
      "IoCategory": "Digital Input"
    },
    {
      "Address": "X211",
      "Index": "DI_PRESSURE_SW4_VACUUM_CV_P",
      "Description": "Pressure Switch <4>",
      "Type": "N.O",
      "IoCategory": "Digital Input"
    },
    {
      "Address": "X212",
      "Index": "DI_PRESSURE_SW5_NORMAL_CV_P_AIR_SPRING",
      "Description": "Pressure Switch <5>",
      "Type": "N.O",
      "IoCategory": "Digital Input"
    },
    {
      "Address": "X213",
      "Index": "DI_PRESSURE_SW6_VACUUM_CV_POROUS_EJEC",
      "Description": "Pressure Switch <6>",
      "Type": "N.O",
      "IoCategory": "Digital Input"
    },
    {
      "Address": "X214",
      "Index": "DI_PRESSURE_SW7_EJEC_ELEC_BOX",
      "Description": "Pressure Switch <7>",
      "Type": "N.O",
      "IoCategory": "Digital Input"
    },
    {
      "Address": "X215",
      "Index": "DI_PRESSURE_SW11_EJEC_VAC_ELEC_BOX",
      "Description": "Pressure Switch <11>",
      "Type": "N.O",
      "IoCategory": "Digital Input"
    },
    {
      "Address": "X216",
      "Index": "DI_DOOR_LOCK_BACK_DOWN_LEFT",
      "Description": "DOOR LOCK CHECK",
      "Type": "N.O",
      "IoCategory": "Digital Input"
    },
    {
      "Address": "X217",
      "Index": "DI_DOOR_LOCK_BACK_DOWN_RIGHT",
      "Description": "DOOR LOCK CHECK",
      "Type": "N.O",
      "IoCategory": "Digital Input"
    },
    {
      "Address": "X300",
      "Index": "DI_VC_ALIGNER_SENSOR_FRONT_1_BACKWARD",
      "Description": "FRONT_1 BACKWARD",
      "Type": "N.O",
      "IoCategory": "Digital Input"
    },
    {
      "Address": "X301",
      "Index": "DI_VC_ALIGNER_SENSOR_FRONT_2_BACKWARD",
      "Description": "FRONT_2 BACKWARD",
      "Type": "N.O",
      "IoCategory": "Digital Input"
    },
    {
      "Address": "X302",
      "Index": "DI_VC_ALIGNER_SENSOR_BACK_1_FORWARD",
      "Description": "BACK_1 FORWARD",
      "Type": "N.O",
      "IoCategory": "Digital Input"
    },
    {
      "Address": "X303",
      "Index": "DI_VC_ALIGNER_SENSOR_BACK_2_FORWARD",
      "Description": "BACK_2 FORWARD",
      "Type": "N.O",
      "IoCategory": "Digital Input"
    },
    {
      "Address": "X304",
      "Index": "DI_VC_ALIGNER_SENSOR_FRONT_1_FORWARD",
      "Description": "FRONT_1 FORWARD",
      "Type": "N.O",
      "IoCategory": "Digital Input"
    },
    {
      "Address": "X305",
      "Index": "DI_VC_ALIGNER_SENSOR_FRONT_2_FORWARD",
      "Description": "FRONT_2 FORWARD",
      "Type": "N.O",
      "IoCategory": "Digital Input"
    },
    {
      "Address": "X306",
      "Index": "DI_VC_ALIGNER_SENSOR_BACK_1_BACKWARD",
      "Description": "BACK_1 BACKWARD",
      "Type": "N.O",
      "IoCategory": "Digital Input"
    },
    {
      "Address": "X307",
      "Index": "DI_VC_ALIGNER_SENSOR_BACK_2_BACKWARD",
      "Description": "BACK_2 BACKWARD",
      "Type": "N.O",
      "IoCategory": "Digital Input"
    },
    {
      "Address": "X308",
      "Index": "DI_VC_ALIGNER_SENSOR_LEFT_1_FORWARD",
      "Description": "LEFT_1 FORWARD",
      "Type": "N.O",
      "IoCategory": "Digital Input"
    },
    {
      "Address": "X309",
      "Index": "DI_VC_ALIGNER_SENSOR_LEFT_2_FORWARD",
      "Description": "LEFT_2 FORWARD",
      "Type": "N.O",
      "IoCategory": "Digital Input"
    },
    {
      "Address": "X310",
      "Index": "DI_VC_ALIGNER_SENSOR_RIGHT_1_FORWARD",
      "Description": "RIGHT_1 FORWARD",
      "Type": "N.O",
      "IoCategory": "Digital Input"
    },
    {
      "Address": "X311",
      "Index": "DI_VC_ALIGNER_SENSOR_RIGHT_2_FORWARD",
      "Description": "RIGHT_2 FORWARD",
      "Type": "N.O",
      "IoCategory": "Digital Input"
    },
    {
      "Address": "X312",
      "Index": "DI_VC_ALIGNER_SENSOR_LEFT_1_BACKWARD",
      "Description": "LEFT_1 BACKWARD",
      "Type": "N.O",
      "IoCategory": "Digital Input"
    },
    {
      "Address": "X313",
      "Index": "DI_VC_ALIGNER_SENSOR_LEFT_2_BACKWARD",
      "Description": "LEFT_2 BACKWARD",
      "Type": "N.O",
      "IoCategory": "Digital Input"
    },
    {
      "Address": "X314",
      "Index": "DI_VC_ALIGNER_SENSOR_RIGHT_1_BACKWARD",
      "Description": "RIGHT_1 BACKWARD",
      "Type": "N.O",
      "IoCategory": "Digital Input"
    },
    {
      "Address": "X315",
      "Index": "DI_VC_ALIGNER_SENSOR_RIGHT_2_BACKWARD",
      "Description": "RIGHT_2 BACKWARD",
      "Type": "N.O",
      "IoCategory": "Digital Input"
    },
    {
      "Address": "X316",
      "Index": "DI_VC_ALIGNER_SENSOR_FRONT_1_UP",
      "Description": "FRONT_1 UP",
      "Type": "N.O",
      "IoCategory": "Digital Input"
    },
    {
      "Address": "X317",
      "Index": "DI_VC_ALIGNER_SENSOR_FRONT_2_UP",
      "Description": "FRONT_2 UP",
      "Type": "N.O",
      "IoCategory": "Digital Input"
    },
    {
      "Address": "X318",
      "Index": "DI_VC_ALIGNER_SENSOR_BACK_1_UP",
      "Description": "BACK_1 UP",
      "Type": "N.O",
      "IoCategory": "Digital Input"
    },
    {
      "Address": "X319",
      "Index": "DI_VC_ALIGNER_SENSOR_BACK_2_UP",
      "Description": "BACK_2 UP",
      "Type": "N.O",
      "IoCategory": "Digital Input"
    },
    {
      "Address": "X320",
      "Index": "DI_VC_ALIGNER_SENSOR_FRONT_1_DOWN",
      "Description": "FRONT_1 DOWN",
      "Type": "N.O",
      "IoCategory": "Digital Input"
    },
    {
      "Address": "X321",
      "Index": "DI_VC_ALIGNER_SENSOR_FRONT_2_DOWN",
      "Description": "FRONT_2 DOWN",
      "Type": "N.O",
      "IoCategory": "Digital Input"
    },
    {
      "Address": "X322",
      "Index": "DI_VC_ALIGNER_SENSOR_BACK_1_DOWN",
      "Description": "BACK_1 DOWN",
      "Type": "N.O",
      "IoCategory": "Digital Input"
    },
    {
      "Address": "X323",
      "Index": "DI_VC_ALIGNER_SENSOR_BACK_2_DOWN",
      "Description": "BACK_2 DOWN",
      "Type": "N.O",
      "IoCategory": "Digital Input"
    },
    {
      "Address": "X324",
      "Index": "DI_VC_ALIGNER_SENSOR_LEFT_1_UP",
      "Description": "LEFT_1 UP",
      "Type": "N.O",
      "IoCategory": "Digital Input"
    },
    {
      "Address": "X325",
      "Index": "DI_VC_ALIGNER_SENSOR_LEFT_2_UP",
      "Description": "LEFT_2 UP",
      "Type": "N.O",
      "IoCategory": "Digital Input"
    },
    {
      "Address": "X326",
      "Index": "DI_VC_ALIGNER_SENSOR_RIGHT_1_UP",
      "Description": "RIGHT_1 UP",
      "Type": "N.O",
      "IoCategory": "Digital Input"
    },
    {
      "Address": "X327",
      "Index": "DI_VC_ALIGNER_SENSOR_RIGHT_2_UP",
      "Description": "RIGHT_2 UP",
      "Type": "N.O",
      "IoCategory": "Digital Input"
    },
    {
      "Address": "X328",
      "Index": "DI_VC_ALIGNER_SENSOR_LEFT_1_DOWN",
      "Description": "LEFT_1 DOWN",
      "Type": "N.O",
      "IoCategory": "Digital Input"
    },
    {
      "Address": "X329",
      "Index": "DI_VC_ALIGNER_SENSOR_LEFT_2_DOWN",
      "Description": "LEFT_2 DOWN",
      "Type": "N.O",
      "IoCategory": "Digital Input"
    },
    {
      "Address": "X330",
      "Index": "DI_VC_ALIGNER_SENSOR_RIGHT_1_DOWN",
      "Description": "RIGHT_1 DOWN",
      "Type": "N.O",
      "IoCategory": "Digital Input"
    },
    {
      "Address": "X331",
      "Index": "DI_VC_ALIGNER_SENSOR_RIGHT_2_DOWN",
      "Description": "RIGHT_2 DOWN",
      "Type": "N.O",
      "IoCategory": "Digital Input"
    },
    {
      "Address": "X332",
      "Index": "DI_VC_SENSOR_ROLLER_UP",
      "Description": "ROLLER UP",
      "Type": "N.O",
      "IoCategory": "Digital Input"
    },
    {
      "Address": "X333",
      "Index": "DI_VC_SENSOR_ROLLER_DOWN",
      "Description": "ROLLER DOWN",
      "Type": "N.O",
      "IoCategory": "Digital Input"
    },
    {
      "Address": "X334",
      "Index": "DI_VC_SENSOR_GLASS_INPUT",
      "Description": "GLASS INPUT",
      "Type": "N.O",
      "IoCategory": "Digital Input"
    },
    {
      "Address": "X335",
      "Index": "DI_VC_SENSOR_GLASS_DECELERATION",
      "Description": "GLASS DECELERATION",
      "Type": "N.O",
      "IoCategory": "Digital Input"
    },
    {
      "Address": "X336",
      "Index": "DI_VC_SENSOR_GLASS_STOP",
      "Description": "GLASS STOP",
      "Type": "N.O",
      "IoCategory": "Digital Input"
    },
    {
      "Address": "X337",
      "Index": "DI_VC_SENSOR_GLASS_BACK_DETECT",
      "Description": "GLASS BACK DETECT",
      "Type": "N.O",
      "IoCategory": "Digital Input"
    },
    {
      "Address": "X338",
      "Index": "DI_VC_SENSOR_GLASS_FRONT_DETECT",
      "Description": "GLASS FRONT DETECT",
      "Type": "N.O",
      "IoCategory": "Digital Input"
    },
    {
      "Address": "X339",
      "Index": "DI_NC_ALIGNER_SENSOR_LEFT_1_UP",
      "Description": "LEFT_1 UP",
      "Type": "N.O",
      "IoCategory": "Digital Input"
    },
    {
      "Address": "X340",
      "Index": "DI_NC_ALIGNER_SENSOR_LEFT_2_UP",
      "Description": "LEFT_2 UP",
      "Type": "N.O",
      "IoCategory": "Digital Input"
    },
    {
      "Address": "X341",
      "Index": "DI_NC_ALIGNER_SENSOR_RIGHT_1_UP",
      "Description": "RIGHT_1 UP",
      "Type": "N.O",
      "IoCategory": "Digital Input"
    },
    {
      "Address": "X342",
      "Index": "DI_NC_ALIGNER_SENSOR_RIGHT_2_UP",
      "Description": "RIGHT_2 UP",
      "Type": "N.O",
      "IoCategory": "Digital Input"
    },
    {
      "Address": "X343",
      "Index": "DI_NC_ALIGNER_SENSOR_LEFT_1_DOWN",
      "Description": "LEFT_1 DOWN",
      "Type": "N.O",
      "IoCategory": "Digital Input"
    },
    {
      "Address": "X344",
      "Index": "DI_NC_ALIGNER_SENSOR_LEFT_2_DOWN",
      "Description": "LEFT_2 DOWN",
      "Type": "N.O",
      "IoCategory": "Digital Input"
    },
    {
      "Address": "X345",
      "Index": "DI_NC_ALIGNER_SENSOR_RIGHT_1_DOWN",
      "Description": "RIGHT_1 DOWN",
      "Type": "N.O",
      "IoCategory": "Digital Input"
    },
    {
      "Address": "X346",
      "Index": "DI_NC_ALIGNER_SENSOR_RIGHT_2_DOWN",
      "Description": "RIGHT_2 DOWN",
      "Type": "N.O",
      "IoCategory": "Digital Input"
    },
    {
      "Address": "X347",
      "Index": "DI_NC_STOPPER_SENSOR_LEFT_FORWARD",
      "Description": "LEFT FORWARD",
      "Type": "N.O",
      "IoCategory": "Digital Input"
    },
    {
      "Address": "X348",
      "Index": "DI_NC_STOPPER_SENSOR_RIGHT_FORWARD",
      "Description": "RIGHT FORWARD",
      "Type": "N.O",
      "IoCategory": "Digital Input"
    },
    {
      "Address": "X349",
      "Index": "DI_NC_STOPPER_SENSOR_LEFT_BACKWARD",
      "Description": "LEFT BACKWARD",
      "Type": "N.O",
      "IoCategory": "Digital Input"
    },
    {
      "Address": "X350",
      "Index": "DI_NC_STOPPER_SENSOR_RIGHT_BACKWARD",
      "Description": "RIGHT BACKWARD",
      "Type": "N.O",
      "IoCategory": "Digital Input"
    },
    {
      "Address": "X351",
      "Index": "DI_NC_STOPPER_SENSOR_LEFT_UP",
      "Description": "LEFT UP",
      "Type": "N.O",
      "IoCategory": "Digital Input"
    },
    {
      "Address": "X352",
      "Index": "DI_NC_STOPPER_SENSOR_RIGHT_UP",
      "Description": "RIGHT UP",
      "Type": "N.O",
      "IoCategory": "Digital Input"
    },
    {
      "Address": "X353",
      "Index": "DI_NC_STOPPER_SENSOR_LEFT_DOWN",
      "Description": "LEFT DOWN",
      "Type": "N.O",
      "IoCategory": "Digital Input"
    },
    {
      "Address": "X354",
      "Index": "DI_NC_STOPPER_SENSOR_RIGHT_DOWN",
      "Description": "RIGHT DOWN",
      "Type": "N.O",
      "IoCategory": "Digital Input"
    },
    {
      "Address": "X355",
      "Index": "DI_CHUCK_UP",
      "Description": "CHUCK UP",
      "Type": "N.O",
      "IoCategory": "Digital Input"
    },
    {
      "Address": "X356",
      "Index": "DI_CHUCK_DOWN",
      "Description": "CHUCK DOWN",
      "Type": "N.O",
      "IoCategory": "Digital Input"
    },
    {
      "Address": "X357",
      "Index": "DI_NC_SENSOR_GLASS_IN_OUTPUT_1",
      "Description": "GLASS IN/OUTPUT_1",
      "Type": "N.O",
      "IoCategory": "Digital Input"
    },
    {
      "Address": "X358",
      "Index": "DI_NC_SENSOR_GLASS_IN_OUTPUT_2",
      "Description": "GLASS IN/OUTPUT_2",
      "Type": "N.O",
      "IoCategory": "Digital Input"
    },
    {
      "Address": "X359",
      "Index": "DI_NC_SENSOR_GLASS_DECELERATION",
      "Description": "GLASS DECELERATION",
      "Type": "N.O",
      "IoCategory": "Digital Input"
    },
    {
      "Address": "X360",
      "Index": "DI_NC_SENSOR_GLASS_STOP",
      "Description": "GLASS STOP",
      "Type": "N.O",
      "IoCategory": "Digital Input"
    },
    {
      "Address": "X361",
      "Index": "DI_NC_SENSOR_GLASS_DETECT",
      "Description": "GLASS DETECT",
      "Type": "N.O",
      "IoCategory": "Digital Input"
    },
    {
      "Address": "X362",
      "Index": "DI_ROLL_WIPER_LOW_DETECT_SENSOR",
      "Description": "Roll Wiper Low",
      "Type": "N.O",
      "IoCategory": "Digital Input"
    },
    {
      "Address": "X363",
      "Index": "DI_ROLL_WIPER_MIDDLE_DETECT_SENSOR",
      "Description": "Roll Wiper Mid",
      "Type": "N.O",
      "IoCategory": "Digital Input"
    },
    {
      "Address": "X364",
      "Index": "DI_BT_CY_SENSOR_AUTOSWITCH_ROLL_UP",
      "Description": "AUTOSWITCH ROLL UP",
      "Type": "N.O",
      "IoCategory": "Digital Input"
    },
    {
      "Address": "X365",
      "Index": "DI_BT_CY_SENSOR_AUTOSWITCH_ROLL_DOWN",
      "Description": "AUTOSWITCH ROLL DOWN",
      "Type": "N.O",
      "IoCategory": "Digital Input"
    },
    {
      "Address": "X366",
      "Index": "DI_PRESSURE_VC_POROUS_VACUUM_EJECT_8",
      "Description": "Pressure Switch <8>",
      "Type": "N.O",
      "IoCategory": "Digital Input"
    },
    {
      "Address": "X367",
      "Index": "DI_MT_SPT_OVERFLOW_SENSOR",
      "Description": "M/T Separator Overflow",
      "Type": "N.O",
      "IoCategory": "Digital Input"
    },
    {
      "Address": "X372",
      "Index": "DI_BOTTLE2_MT_LEVEL_SENSOR_HIGH",
      "Description": "Level Sensor HIGH",
      "Type": "N.C",
      "IoCategory": "Digital Input"
    },
    {
      "Address": "X373",
      "Index": "DI_BOTTLE2_MT_DETECT_SENSOR",
      "Description": "Detect Sensor",
      "Type": "N.C",
      "IoCategory": "Digital Input"
    },
    {
      "Address": "X374",
      "Index": "DI_BOTTLE2_MT_LEAK_SENSOR",
      "Description": "Leak Sensor",
      "Type": "N.C",
      "IoCategory": "Digital Input"
    },
    {
      "Address": "X375",
      "Index": "DI_BOTTLE3_MT_LEVEL_SENSOR_HIGH",
      "Description": "Level Sensor HIGH",
      "Type": "N.C",
      "IoCategory": "Digital Input"
    },
    {
      "Address": "X376",
      "Index": "DI_BOTTLE3_MT_DETECT_SENSOR",
      "Description": "Detect Sensor",
      "Type": "N.C",
      "IoCategory": "Digital Input"
    },
    {
      "Address": "X377",
      "Index": "DI_BOTTLE3_MT_LEAK_SENSOR",
      "Description": "Leak Sensor",
      "Type": "N.C",
      "IoCategory": "Digital Input"
    },
    {
      "Address": "X501",
      "Index": "DI_RESERVOIR_OVERFLOW_1",
      "Description": "RESERVOIR OVERFLOW",
      "Type": "N.C",
      "IoCategory": "Digital Input"
    },
    {
      "Address": "X502",
      "Index": "DI_RESERVOIR_HIGH_1",
      "Description": "RESERVOIR HIGH LEVEL",
      "Type": "N.C",
      "IoCategory": "Digital Input"
    },
    {
      "Address": "X503",
      "Index": "DI_RESERVOIR_SET_1",
      "Description": "RESERVOIR SET LEVEL",
      "Type": "N.C",
      "IoCategory": "Digital Input"
    },
    {
      "Address": "X504",
      "Index": "DI_RESERVOIR_EMPTY_1",
      "Description": "RESERVOIR EMPTY LEVEL",
      "Type": "N.O",
      "IoCategory": "Digital Input"
    },
    {
      "Address": "X600",
      "Index": "DI_BOTTLE4_HM_LEVEL_SENSOR_LOW",
      "Description": "Level Sensor LOW",
      "Type": "N.C",
      "IoCategory": "Digital Input"
    },
    {
      "Address": "X601",
      "Index": "DI_BOTTLE4_MT_DETECT_SENSOR",
      "Description": "Detect Sensor",
      "Type": "N.C",
      "IoCategory": "Digital Input"
    },
    {
      "Address": "X602",
      "Index": "DI_BOTTLE4_MT_LEAK_SENSOR",
      "Description": "Leak Sensor",
      "Type": "N.C",
      "IoCategory": "Digital Input"
    },
    {
      "Address": "X603",
      "Index": "DI_PRESSURE_SW9_IMS_P_N2",
      "Description": "Pressure Switch <9>",
      "Type": "N.O",
      "IoCategory": "Digital Input"
    },
    {
      "Address": "X604",
      "Index": "DI_PRESSURE_SW9_IMS_N_VAC",
      "Description": "Pressure Switch <10>",
      "Type": "N.O",
      "IoCategory": "Digital Input"
    },
    {
      "Address": "Y100",
      "Index": "DO_DOOR_OPEN_SIGNAL",
      "Description": "Door Open Signal",
      "Type": "N.O",
      "IoCategory": "Digital Output"
    },
    {
      "Address": "Y101",
      "Index": "DO_MANUAL_OPEN_INTERLOCK",
      "Description": "Door Manual Interlock",
      "Type": "N.C",
      "IoCategory": "Digital Output"
    },
    {
      "Address": "Y102",
      "Index": "DO_TOWER_LAMP_RED",
      "Description": "Tower Lamp Red",
      "Type": "N.O",
      "IoCategory": "Digital Output"
    },
    {
      "Address": "Y103",
      "Index": "DO_TOWER_LAMP_YELLOW",
      "Description": "Tower Lamp Yellow",
      "Type": "N.O",
      "IoCategory": "Digital Output"
    },
    {
      "Address": "Y104",
      "Index": "DO_TOWER_LAMP_GREEN",
      "Description": "Tower Lamp Green",
      "Type": "N.O",
      "IoCategory": "Digital Output"
    },
    {
      "Address": "Y105",
      "Index": "DO_BUZZER",
      "Description": "Buzzer",
      "Type": "N.O",
      "IoCategory": "Digital Output"
    },
    {
      "Address": "Y107",
      "Index": "DO_SAFETY_KEY_ON",
      "Description": "SAFETY KEY ON",
      "Type": "N.O",
      "IoCategory": "Digital Output"
    },
    {
      "Address": "Y208",
      "Index": "DO_VALVE_REG_7_TO_EJTC_SUPPLY",
      "Description": "Reg<7> to Ejector",
      "Type": "N.O",
      "IoCategory": "Digital Output"
    },
    {
      "Address": "Y209",
      "Index": "DO_VALVE_SEPARATOR_TO_DRAIN_BOTTLE",
      "Description": "Separator to Drain",
      "Type": "N.O",
      "IoCategory": "Digital Output"
    },
    {
      "Address": "Y300",
      "Index": "DO_VC_ALIGNER_SENSOR_ROLLER_UP",
      "Description": "V/C ROLLER UP",
      "Type": "N.O",
      "IoCategory": "Digital Output"
    },
    {
      "Address": "Y301",
      "Index": "DO_VC_ALIGNER_SENSOR_ROLLER_DOWN",
      "Description": "V/C ROLLER DOWN",
      "Type": "N.O",
      "IoCategory": "Digital Output"
    },
    {
      "Address": "Y302",
      "Index": "DO_VC_ALIGNER_FB_FORWARD",
      "Description": "FRONT/BACK FORWARD",
      "Type": "N.O",
      "IoCategory": "Digital Output"
    },
    {
      "Address": "Y303",
      "Index": "DO_VC_ALIGNER_FB_BACKWARD",
      "Description": "FRONT/BACK BACKWARD",
      "Type": "N.O",
      "IoCategory": "Digital Output"
    },
    {
      "Address": "Y304",
      "Index": "DO_VC_ALIGNER_LR_FORWARD",
      "Description": "LEFT/RIGHT FORWARD",
      "Type": "N.O",
      "IoCategory": "Digital Output"
    },
    {
      "Address": "Y305",
      "Index": "DO_VC_ALIGNER_LR_BACKWARD",
      "Description": "LEFT/RIGHT BACKWARD",
      "Type": "N.O",
      "IoCategory": "Digital Output"
    },
    {
      "Address": "Y306",
      "Index": "DO_VC_ALIGNER_FB_UP",
      "Description": "FRONT/BACK UP",
      "Type": "N.O",
      "IoCategory": "Digital Output"
    },
    {
      "Address": "Y307",
      "Index": "DO_VC_ALIGNER_FB_DOWN",
      "Description": "FRONT/BACK DOWN",
      "Type": "N.O",
      "IoCategory": "Digital Output"
    },
    {
      "Address": "Y308",
      "Index": "DO_VC_ALIGNER_LR_UP",
      "Description": "LEFT/RIGHT UP",
      "Type": "N.O",
      "IoCategory": "Digital Output"
    },
    {
      "Address": "Y309",
      "Index": "DO_VC_ALIGNER_LR_DOWN",
      "Description": "LEFT/RIGHT DOWN",
      "Type": "N.O",
      "IoCategory": "Digital Output"
    },
    {
      "Address": "Y310",
      "Index": "DO_VC_SENSOR_BLOWER",
      "Description": "V/C SENSOR BLOWER",
      "Type": "N.O",
      "IoCategory": "Digital Output"
    },
    {
      "Address": "Y312",
      "Index": "DO_NC_ALIGNER_LR_DOWN",
      "Description": "L/R DOWN",
      "Type": "N.O",
      "IoCategory": "Digital Output"
    },
    {
      "Address": "Y313",
      "Index": "DO_NC_STOPPER_LR_FORWARD",
      "Description": "L/R FORWARD",
      "Type": "N.O",
      "IoCategory": "Digital Output"
    },
    {
      "Address": "Y314",
      "Index": "DO_NC_STOPPER_LR_BACKWARD",
      "Description": "L/R BACKWARD",
      "Type": "N.O",
      "IoCategory": "Digital Output"
    },
    {
      "Address": "Y315",
      "Index": "DO_NC_STOPPER_LR_UP",
      "Description": "L/R UP",
      "Type": "N.O",
      "IoCategory": "Digital Output"
    },
    {
      "Address": "Y316",
      "Index": "DO_NC_STOPPER_LR_DOWN",
      "Description": "L/R DOWN",
      "Type": "N.O",
      "IoCategory": "Digital Output"
    },
    {
      "Address": "Y317",
      "Index": "DO_NC_STOPPER_CHUCK_UP",
      "Description": "N/C CHUCK UP",
      "Type": "N.O",
      "IoCategory": "Digital Output"
    },
    {
      "Address": "Y318",
      "Index": "DO_NC_STOPPER_CHUCK_DOWN",
      "Description": "N/C CHUCK DOWN",
      "Type": "N.O",
      "IoCategory": "Digital Output"
    },
    {
      "Address": "Y319",
      "Index": "DO_NC_SENSOR_BLOWER",
      "Description": "N/C SENSOR BLOWER",
      "Type": "N.O",
      "IoCategory": "Digital Output"
    },
    {
      "Address": "Y324",
      "Index": "DO_VC_CHUCK_VAC_SUPPLY",
      "Description": "EJECTOR SUPPLY",
      "Type": "N.O",
      "IoCategory": "Digital Output"
    },
    {
      "Address": "Y325",
      "Index": "DO_VC_CHUCK_VAC_BREAK",
      "Description": "EJECTOR BREAK",
      "Type": "N.O",
      "IoCategory": "Digital Output"
    },
    {
      "Address": "Y332",
      "Index": "DO_NC_CHUCK_VACUUM_ON",
      "Description": "N/C CHUCK VAC ON",
      "Type": "N.O",
      "IoCategory": "Digital Output"
    },
    {
      "Address": "Y333",
      "Index": "DO_SUCTION_TO_SPT",
      "Description": "Suction Bath To Spt",
      "Type": "N.O",
      "IoCategory": "Digital Output"
    },
    {
      "Address": "Y334",
      "Index": "DO_PURGE_TO_SPT",
      "Description": "Purge Bath To Spt",
      "Type": "N.O",
      "IoCategory": "Digital Output"
    },
    {
      "Address": "Y335",
      "Index": "DO_BATH_TO_DRAIN_PUMP",
      "Description": "Bath To Drain Pump",
      "Type": "N.O",
      "IoCategory": "Digital Output"
    },
    {
      "Address": "Y336",
      "Index": "DO_DIE_TO_DRAIN_PUMP",
      "Description": "Slot Die To Drain Pump",
      "Type": "N.O",
      "IoCategory": "Digital Output"
    },
    {
      "Address": "Y340",
      "Index": "DO_BLOTTER_ROLL_UP",
      "Description": "BLOTTER ROLL UP",
      "Type": "N.O",
      "IoCategory": "Digital Output"
    },
    {
      "Address": "Y341",
      "Index": "DO_BLOTTER_ROLL_DOWN",
      "Description": "BLOTTER ROLL DOWN",
      "Type": "N.O",
      "IoCategory": "Digital Output"
    },
    {
      "Address": "Y600",
      "Index": "DO_AIR_KNIFE_VALVE",
      "Description": "AIR KNIFE V/V",
      "Type": "N.C",
      "IoCategory": "Digital Output"
    },
    {
      "Address": "Y700",
      "Index": "DO_PACK1_H1_IN",
      "Description": "Pack 1 H1 In",
      "Type": "N.O",
      "IoCategory": "Digital Output"
    },
    {
      "Address": "Y701",
      "Index": "DO_PACK1_H1_OUT",
      "Description": "Pack 1 H1 Out",
      "Type": "N.O",
      "IoCategory": "Digital Output"
    },
    {
      "Address": "Y702",
      "Index": "DO_PACK1_H2_IN",
      "Description": "Pack 1 H2 In",
      "Type": "N.O",
      "IoCategory": "Digital Output"
    },
    {
      "Address": "Y703",
      "Index": "DO_PACK1_H2_OUT",
      "Description": "Pack 1 H2 Out",
      "Type": "N.O",
      "IoCategory": "Digital Output"
    },
    {
      "Address": "Y704",
      "Index": "DO_PACK1_H3_IN",
      "Description": "Pack 1 H3 In",
      "Type": "N.O",
      "IoCategory": "Digital Output"
    },
    {
      "Address": "Y705",
      "Index": "DO_PACK1_H3_OUT",
      "Description": "Pack 1 H3 Out",
      "Type": "N.O",
      "IoCategory": "Digital Output"
    },
    {
      "Address": "Y706",
      "Index": "DO_PACK1_H4_IN",
      "Description": "Pack 1 H4 In",
      "Type": "N.O",
      "IoCategory": "Digital Output"
    },
    {
      "Address": "Y707",
      "Index": "DO_PACK1_H4_OUT",
      "Description": "Pack 1 H4 Out",
      "Type": "N.O",
      "IoCategory": "Digital Output"
    },
    {
      "Address": "Y708",
      "Index": "DO_PACK1_H5_IN",
      "Description": "Pack 1 H5 In",
      "Type": "N.O",
      "IoCategory": "Digital Output"
    },
    {
      "Address": "Y709",
      "Index": "DO_PACK1_H5_OUT",
      "Description": "Pack 1 H5 Out",
      "Type": "N.O",
      "IoCategory": "Digital Output"
    },
    {
      "Address": "Y710",
      "Index": "DO_PACK1_H6_IN",
      "Description": "Pack 1 H6 In",
      "Type": "N.O",
      "IoCategory": "Digital Output"
    },
    {
      "Address": "Y711",
      "Index": "DO_PACK1_H6_OUT",
      "Description": "Pack 1 H6 Out",
      "Type": "N.O",
      "IoCategory": "Digital Output"
    },
    {
      "Address": "Y712",
      "Index": "DO_PACK1_H7_IN",
      "Description": "Pack 1 H7 In",
      "Type": "N.O",
      "IoCategory": "Digital Output"
    },
    {
      "Address": "Y713",
      "Index": "DO_PACK1_H7_OUT",
      "Description": "Pack 1 H7 Out",
      "Type": "N.O",
      "IoCategory": "Digital Output"
    },
    {
      "Address": "Y714",
      "Index": "DO_PACK1_H8_IN",
      "Description": "Pack 1 H8 In",
      "Type": "N.O",
      "IoCategory": "Digital Output"
    },
    {
      "Address": "Y715",
      "Index": "DO_PACK1_H8_OUT",
      "Description": "Pack 1 H8 Out",
      "Type": "N.O",
      "IoCategory": "Digital Output"
    },
    {
      "Address": "Y716",
      "Index": "DO_BOTTLE_INK_SUPPLY",
      "Description": "Ink Supply Valve",
      "Type": "N.O",
      "IoCategory": "Digital Output"
    },
    {
      "Address": "Y717",
      "Index": "DO_UP_PLATE_COOLING",
      "Description": "Up Plate Cooling",
      "Type": "N.O",
      "IoCategory": "Digital Output"
    },
    {
      "Address": "Y718",
      "Index": "DO_DOWN_PLATE_COOLING",
      "Description": "Down Plate Cooling",
      "Type": "N.O",
      "IoCategory": "Digital Output"
    }
  ],
  "Analog_IO_List": [
    {
      "Address": "Y7000",
      "Index": "AO_CH_1_TARGET_MENISCUS",
      "Description": "MPC Meniscus Set",
      "Type": "UINT",
      "IoCategory": "Analog Output"
    },
    {
      "Address": "Y7001",
      "Index": "AO_CH_1_TARGET_PURGE",
      "Description": "MPC Purge Set",
      "Type": "UINT",
      "IoCategory": "Analog Output"
    },
    {
      "Address": "Y7002",
      "Index": "AO_CH_1_TARGET_PUMP",
      "Description": "Pump Set",
      "Type": "UINT",
      "IoCategory": "Analog Output"
    },
    {
      "Address": "Y7003",
      "Index": "AO_CH_1_TARGET_HEATER",
      "Description": "Heater Set",
      "Type": "UINT",
      "IoCategory": "Analog Output"
    },
    {
      "Address": "Y7004",
      "Index": "AO_CH_1_AO_Ch_0",
      "Description": "AO Ch0",
      "Type": "UINT",
      "IoCategory": "Analog Output"
    },
    {
      "Address": "Y7005",
      "Index": "AO_CH_1_AO_Ch_1",
      "Description": "AO Ch1",
      "Type": "UINT",
      "IoCategory": "Analog Output"
    },
    {
      "Address": "X6001",
      "Index": "AI_CH_1_MENISCUS_PRESSURE",
      "Description": "Meniscus Set Pressure",
      "Type": "UINT",
      "IoCategory": "Analog Input"
    },
    {
      "Address": "X6002",
      "Index": "AI_CH_1_PURGE_PRESSURE",
      "Description": "Purge Set Pressure",
      "Type": "UINT",
      "IoCategory": "Analog Input"
    },
    {
      "Address": "X6003",
      "Index": "AI_CH_1_PUMP_FLOW",
      "Description": "Pump Prosent Flow",
      "Type": "UINT",
      "IoCategory": "Analog Input"
    },
    {
      "Address": "X6004",
      "Index": "AI_CH_1_HEATER_TEMP",
      "Description": "Heater Temperature",
      "Type": "UINT",
      "IoCategory": "Analog Input"
    },
    {
      "Address": "X6005",
      "Index": "AI_CH_1_AI_Ch0",
      "Description": "AI Ch0",
      "Type": "UINT",
      "IoCategory": "Analog Input"
    },
    {
      "Address": "X6006",
      "Index": "AI_CH_1_AI_Ch1",
      "Description": "AI Ch1",
      "Type": "UINT",
      "IoCategory": "Analog Input"
    },
    {
      "Address": "X6007",
      "Index": "AI_CH_1_AI_Ch2",
      "Description": "AI Ch2",
      "Type": "UINT",
      "IoCategory": "Analog Input"
    },
    {
      "Address": "X6008",
      "Index": "AI_CH_1_AI_Ch3",
      "Description": "AI Ch3",
      "Type": "UINT",
      "IoCategory": "Analog Input"
    }
  ]
}